shoobx/__init__.py
shoobx/junitxml/__init__.py
shoobx/junitxml/feature.py
shoobx/junitxml/formatter.py
shoobx/junitxml/tests/__init__.py
shoobx/junitxml/tests/test_formatter.py
shoobx.junitxml-0.3.0.dist-info/METADATA
shoobx.junitxml-0.3.0.dist-info/WHEEL
shoobx.junitxml-0.3.0.dist-info/top_level.txt
shoobx.junitxml-0.3.0.dist-info/RECORD
