Metadata-Version: 2.1
Name: shoobx.junitxml
Version: 0.3.0
Summary: A zope.testrunner output formatter & feature to output JUnit XML.
Home-page: https://github.com/shoobx/shoobx.junitxml
Author: Shoobx, Inc. and Martin Aspelli
Author-email: dev@shoobx.com
License: ZPL 2.1
Keywords: jenkins junit xml zope.testing
Classifier: Development Status :: 3 - Alpha
Classifier: Intended Audience :: Developers
Classifier: License :: OSI Approved :: Zope Public License
Classifier: Natural Language :: English
Classifier: Operating System :: OS Independent
Classifier: Programming Language :: Python
Classifier: Programming Language :: Python :: 3.6
Classifier: Programming Language :: Python :: 3.7
Classifier: Programming Language :: Python :: 3.8
Requires-Dist: lxml
Requires-Dist: setuptools
Requires-Dist: zope.testrunner
